s3_prd_crypt/__init__.py
s3_prd_crypt/file_type.py
s3_prd_crypt/prd.py
s3_prd_crypt/s3_connector.py
s3_prd_crypt-0.0.2.dist-info/LICENSE
s3_prd_crypt-0.0.2.dist-info/METADATA
s3_prd_crypt-0.0.2.dist-info/WHEEL
s3_prd_crypt-0.0.2.dist-info/top_level.txt
s3_prd_crypt-0.0.2.dist-info/RECORD
