Metadata-Version: 2.1
Name: s3-prd-crypt
Version: 0.0.2
Summary: UNKNOWN
Home-page: https://github.com/navikt
Author: NAV IKT
License: MIT
Platform: UNKNOWN
Requires-Python: >=3.7
Requires-Dist: pyarrow (==1.0.1)
Requires-Dist: pandas (==1.1.0)
Requires-Dist: boto3 (==1.14.43)
